prefixdate/__init__.py
prefixdate/formats.py
prefixdate/parse.py
prefixdate/precision.py
prefixdate/py.typed
prefixdate-0.5.0.dist-info/METADATA
prefixdate-0.5.0.dist-info/WHEEL
prefixdate-0.5.0.dist-info/licenses/LICENSE
prefixdate-0.5.0.dist-info/RECORD
