Metadata-Version: 2.4
Name: prefixdate
Version: 0.5.0
Summary: Parse and process date string of varied precision as prefixes in Python.
Project-URL: Homepage, http://github.com/pudo/prefixdate
Author-email: Friedrich Lindenberg <friedrich@pudo.org>
License: MIT
License-File: LICENSE
Keywords: date,iso8601,partial date,rfc3339
Classifier: Intended Audience :: Developers
Classifier: License :: OSI Approved :: MIT License
Classifier: Operating System :: OS Independent
Classifier: Programming Language :: Python :: 3.9
Classifier: Programming Language :: Python :: 3.10
Classifier: Programming Language :: Python :: 3.11
Classifier: Programming Language :: Python :: 3.12
Classifier: Programming Language :: Python :: 3.13
Requires-Python: >=3.9
Provides-Extra: dev
Requires-Dist: build; extra == 'dev'
Requires-Dist: bump2version; extra == 'dev'
Requires-Dist: mypy; extra == 'dev'
Requires-Dist: pytest; extra == 'dev'
Requires-Dist: pytest-cov; extra == 'dev'
Requires-Dist: wheel; extra == 'dev'
